<?xml version="1.0" encoding="UTF-8"?>
<persistence version="2.0"
	xmlns="http://java.sun.com/xml/ns/persistence" xmlns:xsi="http://www.w3.org/2001/XMLSchema-instance"
	xsi:schemaLocation="http://java.sun.com/xml/ns/persistence http://java.sun.com/xml/ns/persistence/persistence_2_0.xsd">
	<persistence-unit name="edgo">
		<class>org.c3s.edgo.common.entity.Pilot</class>
		<class>org.c3s.edgo.common.entity.Ship</class>
		<class>org.c3s.edgo.common.entity.ShipSlot</class>
		<class>org.c3s.edgo.common.entity.SlotType</class>
		<class>org.c3s.edgo.common.entity.Slot</class>
		<class>org.c3s.edgo.common.entity.ShipSlotPK</class>
		<class>org.c3s.edgo.common.entity.Module</class>
		<class>org.c3s.edgo.common.entity.ModuleGroup</class>
		<class>org.c3s.edgo.common.entity.Role</class>
		<class>org.c3s.edgo.common.entity.User</class>
		<class>org.c3s.edgo.common.entity.UserKey</class>
		<properties>
			<property name="javax.persistence.jdbc.driver" value="com.mysql.jdbc.Driver" />
			<property name="javax.persistence.jdbc.url" value="jdbc:mysql://localhost:3306/ed-go" />
			<property name="javax.persistence.jdbc.user" value="root" />
			<property name="javax.persistence.jdbc.password" value="root" />
			<property name="hibernate.dialect" value="org.hibernate.dialect.MySQLDialect" />
			<property name="hibernate.hbm2ddl.auto" value="update" />
			<property name="hibernate.show_sql" value="false" />
			<property name="hibernate.format_sql" value="true" />
		</properties>
	</persistence-unit>
<!--
@Table(name="users")
@NamedQueries({
	@NamedQuery(name="User.findAll", query="SELECT u FROM User u"),
	@NamedQuery(name="User.findByUuid", query="SELECT u FROM User u where u.userUuid = :uuid"),
	@NamedQuery(name="User.findByEmailAndPassword", query="SELECT u FROM User u where LOWER(u.email) = LOWER(:email) AND u.uid = :password")
})
-->	
</persistence>
